vanisher/__about__.py
vanisher/__init__.py
vanisher/main.py
wvanisher-1.0.1.dist-info/METADATA
wvanisher-1.0.1.dist-info/WHEEL
wvanisher-1.0.1.dist-info/licenses/LICENSE
wvanisher-1.0.1.dist-info/RECORD
