Metadata-Version: 2.4
Name: wvanisher
Version: 1.0.1
Summary: A flexible configuration management library for Python with dot notation support, environment variable overrides, and more.
Project-URL: Documentation, https://github.com/woidzero/vanisher#readme
Project-URL: Issues, https://github.com/woidzero/vanisher/issues
Project-URL: Source, https://github.com/woidzero/vanisher
Author-email: woidzero <wwwoidzero@gmail.com>
License: MIT License
License-File: LICENSE
Keywords: config,configuration,control,env,json,management,options,parameters
Classifier: Development Status :: 4 - Beta
Classifier: Programming Language :: Python
Classifier: Programming Language :: Python :: 3.8
Classifier: Programming Language :: Python :: 3.9
Classifier: Programming Language :: Python :: 3.10
Classifier: Programming Language :: Python :: 3.11
Classifier: Programming Language :: Python :: 3.12
Classifier: Programming Language :: Python :: 3.13
Classifier: Programming Language :: Python :: Implementation :: CPython
Classifier: Programming Language :: Python :: Implementation :: PyPy
Requires-Python: >=3.7
